mpw.py
mpwalg.py
mpwalg-0.2.3.dist-info/LICENSE
mpwalg-0.2.3.dist-info/METADATA
mpwalg-0.2.3.dist-info/WHEEL
mpwalg-0.2.3.dist-info/top_level.txt
mpwalg-0.2.3.dist-info/RECORD
