Metadata-Version: 2.1
Name: mpwalg
Version: 0.2.3
Summary: Calculate a site's password
Home-page: https://github.com/emiljoha/pympw
Author: Emil Johansson
Author-email: emil.sweden@gmail.com
License: UNKNOWN
Platform: UNKNOWN
License-File: LICENSE
Requires-Dist: scrypt
Requires-Dist: wheel
